<?xml version="1.0" encoding="UTF-8" standalone="yes"?>
<set xmlns:noNamespaceSchemaLocation="CardSet.xsd" name="DMX-19 Super Rare 100% Pack: CoroCoro Edition" id="bd6c7152-d75e-4d02-859f-a78908247c7b" gameId="bb784fc6-fe21-4603-90d7-82c049908a74" gameVersion="3.0.0.0" version="2.0.0.0">
  <cards>
    <card id="b757940f-e594-4331-82c2-4abe80b4bb76" name="Gaial Killer Kaiser, Passion Dragon">
      <property name="Format" value="OCG"/>
      <property name="Civilization" value="Fire"/>
      <property name="Cost" value="9"/>
      <property name="Type" value="Creature"/>
      <property name="Race" value="Gaial Command Dragon"/>
      <property name="Power" value="12000"/>
      <property name="Rules" value="{SPEED ATTACKER} (This creature doesn't get summoning sickness.)&#xA;{TRIPLE BREAKER}&#xA;■ During the turn this creature was put into the battle zone, this creature can attack untapped creatures."/>
      <property name="Watermark" value=""/>
      <property name="Set" value="DMX-19 Super Rare 100% Pack: CoroCoro Edition"/>
      <property name="Number" value="P84"/>
    </card>
  </cards>
</set>