<?xml version="1.0" encoding="UTF-8" standalone="yes"?>
<set xmlns:noNamespaceSchemaLocation="CardSet.xsd" name="DMSD-13 Super GR Mega Start Deck: Joe's Super Jokers Tornado" id="3394cbcc-5aa2-4db1-a901-b918fd816424" gameId="bb784fc6-fe21-4603-90d7-82c049908a74" gameVersion="3.0.0.0" version="2.0.0.0">
  <cards>
    <card id="11125ab5-27ca-47bf-a089-e5795efbeec0" name="Dartanic Beyond, Super Omega Class">
      <property name="Format" value="OCG"/>
      <property name="Civilization" value="Water"/>
      <property name="Cost" value="4"/>
      <property name="Type" value="Gacharange Creature"/>
      <property name="Race" value="Jokers/Wonderforce"/>
      <property name="Power" value="1000+"/>
      <property name="Rules" value="{POWERED BREAKER} (This creature breaks an additional shield for each 6000 power.)&#xA;■ This creature gets +1000 power for each card in your hand.&#xA;■ Whenever this creature attacks, you may jokers tornado. If you do, draw a card. {JOKERS TORNADO} Return one of your other Jokers to your hand"/>
      <property name="Watermark" value=""/>
      <property name="Mana" value="N/A"/>
      <property name="Rarity" value="Super Rare"/>
      <property name="Number" value="1"/>
      <property name="Set" value="DMSD-13 Super GR Mega Start Deck: Joe's Super Jokers Tornado"/>
    </card>
    <card id="65d3c7fa-be32-4a04-b765-89aed5a87b02" name="Poseidon the Gold">
      <property name="Format" value="OCG"/>
      <property name="Civilization" value="Water"/>
      <property name="Cost" value="4"/>
      <property name="Type" value="Creature"/>
      <property name="Race" value="Jokers/Wonderforce"/>
      <property name="Power" value="4000+"/>
      <property name="Rules" value="■ When you put this creature into the battle zone, Gacharange Summon. ({GACHARANGE SUMMON}: Summon the top card of your super gacharange with its cost paid.)&#xA;■ Whenever this creature attacks, you may jokers tornado. If you do, this creature gets +2000 power, &quot;double breaker&quot; and can't be blocked until the end of the turn. {JOKERS TORNADO} Return one of your other Jokers to your hand"/>
      <property name="Watermark" value=""/>
      <property name="Mana" value="1"/>
      <property name="Rarity" value="Super Rare"/>
      <property name="Number" value="2"/>
      <property name="Set" value="DMSD-13 Super GR Mega Start Deck: Joe's Super Jokers Tornado"/>
    </card>
    <card id="b989a879-48b9-462b-be17-451298e9efc5" name="Orechinrenji">
      <property name="Format" value="OCG"/>
      <property name="Civilization" value="Water"/>
      <property name="Cost" value="3"/>
      <property name="Type" value="Gacharange Creature"/>
      <property name="Race" value="Jokers/Wonderforce"/>
      <property name="Power" value="2000"/>
      <property name="Rules" value="■ When you put this creature, look at the top 2 cards of your deck and put one on the bottom of your deck.&#xA;(At the start of the game, gacharange creatures aren't put into your deck and are put into your super gacharange, and if a gacharange creature would be put into a zone other than the battle zone, return them to the bottom of your super gacharange.)"/>
      <property name="Watermark" value=""/>
      <property name="Mana" value="N/A"/>
      <property name="Rarity" value="No Rarity"/>
      <property name="Number" value="3"/>
      <property name="Set" value="DMSD-13 Super GR Mega Start Deck: Joe's Super Jokers Tornado"/>
    </card>
    <card id="576eab6c-c470-47d7-9dd1-255afffa399a" name="Zekkyosuraida">
      <property name="Format" value="OCG"/>
      <property name="Civilization" value="Water"/>
      <property name="Cost" value="6"/>
      <property name="Type" value="Creature"/>
      <property name="Race" value="Jokers"/>
      <property name="Power" value="2000"/>
      <property name="Rules" value="{SHIELD TRIGGER} (When this creature is put into your hand from your shield zone, you may summon it immediately for no cost.)&#xA;■ When you put this creature into the battle zone, choose one of your opponent's creatures and return it to its owner's hand."/>
      <property name="Watermark" value=""/>
      <property name="Mana" value="1"/>
      <property name="Rarity" value="No Rarity"/>
      <property name="Number" value="4"/>
      <property name="Set" value="DMSD-13 Super GR Mega Start Deck: Joe's Super Jokers Tornado"/>
    </card>
    <card id="0c83e250-7d4e-4220-953b-4b8ce2ddf390" name="Madame Perfu">
      <property name="Format" value="OCG"/>
      <property name="Civilization" value="Water"/>
      <property name="Cost" value="5"/>
      <property name="Type" value="Creature"/>
      <property name="Race" value="Jokers/Wonderforce"/>
      <property name="Power" value="2000"/>
      <property name="Rules" value="{SHIELD TRIGGER} (When this creature is put into your hand from your shield zone, you may summon it immediately for no cost.)&#xA;■ When you put this creature into the battle zone, gacharange summon. ({GACHARANGE SUMMON}: Summon the top card of your super gacharange with its cost paid.)"/>
      <property name="Watermark" value=""/>
      <property name="Mana" value="1"/>
      <property name="Rarity" value="No Rarity"/>
      <property name="Number" value="5"/>
      <property name="Set" value="DMSD-13 Super GR Mega Start Deck: Joe's Super Jokers Tornado"/>
    </card>
    <card id="e719a977-650e-4511-a45b-7f1117abbfec" name="Suzie Cue">
      <property name="Format" value="OCG"/>
      <property name="Civilization" value="Water"/>
      <property name="Cost" value="3"/>
      <property name="Type" value="Creature"/>
      <property name="Race" value="Jokers"/>
      <property name="Power" value="3000"/>
      <property name="Rules" value="■ When you put this creature into the battle zone, choose a number. Until the start of your next turn, all your opponent's creatures that cost the same as that number can't attack or block."/>
      <property name="Watermark" value=""/>
      <property name="Mana" value="1"/>
      <property name="Rarity" value="No Rarity"/>
      <property name="Number" value="6"/>
      <property name="Set" value="DMSD-13 Super GR Mega Start Deck: Joe's Super Jokers Tornado"/>
    </card>
    <card id="02531af1-890d-4397-943b-48b387bab66e" name="Bubbleto">
      <property name="Format" value="OCG"/>
      <property name="Civilization" value="Water"/>
      <property name="Cost" value="2"/>
      <property name="Type" value="Creature"/>
      <property name="Race" value="Jokers/Wonderforce"/>
      <property name="Power" value="2000"/>
      <property name="Rules" value="■ Whenever this creature attacks, you may jokers tornado. If you do, gacharange summon. ({GACHARANGE SUMMON}: Summon the top card of your super gacharange with its cost paid.)"/>
      <property name="Watermark" value=""/>
      <property name="Mana" value="1"/>
      <property name="Rarity" value="No Rarity"/>
      <property name="Number" value="7"/>
      <property name="Set" value="DMSD-13 Super GR Mega Start Deck: Joe's Super Jokers Tornado"/>
    </card>
    <card id="ab623b56-5576-4b22-99c8-0b7f5d5ae442" name="Zababan Jokers">
      <property name="Format" value="OCG"/>
      <property name="Civilization" value="Water"/>
      <property name="Cost" value="1"/>
      <property name="Type" value="Spell"/>
      <property name="Race" value="Jokers"/>
      <property name="Rules" value="■ Draw a card, then discard a card. If the discarded card was a Jokers, draw a card."/>
      <property name="Watermark" value=""/>
      <property name="Rarity" value="No Rarity"/>
      <property name="Number" value="8"/>
      <property name="Set" value="DMSD-13 Super GR Mega Start Deck: Joe's Super Jokers Tornado"/>
    </card>
    <card id="36008cef-c7bc-42ff-b2a2-751183f8c3b2" name="Jobato De Runo">
      <property name="Format" value="OCG"/>
      <property name="Civilization" value="Colorless"/>
      <property name="Cost" value="6"/>
      <property name="Type" value="Creature"/>
      <property name="Race" value="Jokers"/>
      <property name="Power" value="1000"/>
      <property name="Rules" value="{SHIELD TRIGGER} (When this creature is put into your hand from your shield zone, you may summon it immediately for no cost.)&#xA;■ When you put this creature into the battle zone, choose a creature and tap it. Then, choose a creature and untap it."/>
      <property name="Watermark" value=""/>
      <property name="Rarity" value="No Rarity"/>
      <property name="Number" value="9"/>
      <property name="Set" value="DMSD-13 Super GR Mega Start Deck: Joe's Super Jokers Tornado"/>
    </card>
    <card id="53f44634-472a-4186-b0e3-5e0ca4bc761d" name="Tutankhanen">
      <property name="Format" value="OCG"/>
      <property name="Civilization" value="Colorless"/>
      <property name="Cost" value="3"/>
      <property name="Type" value="Creature"/>
      <property name="Race" value="Jokers"/>
      <property name="Power" value="1000"/>
      <property name="Rules" value="■ When you put this creature, draw a card."/>
      <property name="Watermark" value=""/>
      <property name="Rarity" value="No Rarity"/>
      <property name="Number" value="10"/>
      <property name="Set" value="DMSD-13 Super GR Mega Start Deck: Joe's Super Jokers Tornado"/>
    </card>
    <card id="9c8098e4-6525-494f-bdf8-fd2d79d4c392" name="Papparapali Nights">
      <property name="Format" value="OCG"/>
      <property name="Civilization" value="Colorless"/>
      <property name="Cost" value="3"/>
      <property name="Type" value="Gacharange Creature"/>
      <property name="Race" value="Jokers/Wonderforce"/>
      <property name="Power" value="2000"/>
      <property name="Rules" value="■ Mana Drive 2 (Jokers): When you put this creature, if you have 2 or more cards in your mana zone and at least one of them is Jokers, put a Jokers from your graveyard into your mana zone.&#xA;(At the start of the game, gacharange creatures aren't put into your deck and are put into your super gacharange, and if a gacharange creature would be put into a zone other than the battle zone, return them to the bottom of your super gacharange.)"/>
      <property name="Watermark" value=""/>
      <property name="Mana" value="N/A"/>
      <property name="Rarity" value="Rare"/>
      <property name="Number" value="11"/>
      <property name="Set" value="DMSD-13 Super GR Mega Start Deck: Joe's Super Jokers Tornado"/>
    </card>
    <card id="9ed7efd9-5ad0-4b7a-a92b-1fbe52114108" name="Bainaradoor">
      <property name="Format" value="OCG"/>
      <property name="Civilization" value="Colorless"/>
      <property name="Cost" value="8"/>
      <property name="Type" value="Creature"/>
      <property name="Race" value="Jokers"/>
      <property name="Power" value="2000"/>
      <property name="Rules" value="{SHIELD TRIGGER} (When this card is put into your hand from your shield zone, you may cast/summon it immediately for no cost.)&#xA;■ When you put this creature, if you have a total of 3 or more Jokers in the battle zone or your mana zone, choose one of your opponent's creatures and put it on the bottom of their deck. Then draw a card."/>
      <property name="Watermark" value=""/>
      <property name="Rarity" value="Rare"/>
      <property name="Number" value="12"/>
      <property name="Set" value="DMSD-13 Super GR Mega Start Deck: Joe's Super Jokers Tornado"/>
    </card>
    <card id="5cecac24-13bd-4d73-9c8e-8e416a93a56e" name="Spongetom">
      <property name="Format" value="OCG"/>
      <property name="Civilization" value="Water"/>
      <property name="Cost" value="2"/>
      <property name="Type" value="Creature"/>
      <property name="Race" value="Jokers"/>
      <property name="Power" value="2000"/>
      <property name="Rules" value="■ Whenever this creature attacks, you may jokers tornado. If you do, draw 2 cards. {JOKERS TORNADO} Return one of your other Jokers to your hand&#xA;■ If you have 5 or more cards in your hand, this creature can't be attacked or blocked."/>
      <property name="Watermark" value=""/>
      <property name="Mana" value="1"/>
      <property name="Rarity" value="Rare"/>
      <property name="Number" value="13"/>
      <property name="Set" value="DMSD-13 Super GR Mega Start Deck: Joe's Super Jokers Tornado"/>
    </card>
    <card id="878e2a63-2076-436d-94cf-4d6261ed52e3" name="Bikubikkun">
      <property name="Format" value="OCG"/>
      <property name="Civilization" value="Water"/>
      <property name="Cost" value="4"/>
      <property name="Type" value="Creature"/>
      <property name="Race" value="Jokers/Wonderforce"/>
      <property name="Power" value="4000"/>
      <property name="Rules" value="■ When this creature or one of your other creatures is returned to your hand from the battle zone, gacharange summon. ({GACHARANGE SUMMON}: Summon the top card of your super gacharange with its cost paid.)"/>
      <property name="Watermark" value=""/>
      <property name="Mana" value="1"/>
      <property name="Rarity" value="Uncommon"/>
      <property name="Number" value="14"/>
      <property name="Set" value="DMSD-13 Super GR Mega Start Deck: Joe's Super Jokers Tornado"/>
    </card>
    <card id="887fa796-7751-49a2-aaab-4c7ee13c191a" name="Yattarerobo">
      <property name="Format" value="OCG"/>
      <property name="Civilization" value="Colorless"/>
      <property name="Cost" value="2"/>
      <property name="Type" value="Gacharange Creature"/>
      <property name="Race" value="Jokers/Wonderforce"/>
      <property name="Power" value="2000"/>
      <property name="Rules" value="■ Your Jokers cost 1 less to summon. They can't cost 0 or less.&#xA;(At the start of the game, gacharange creatures aren't put into your deck and are put into your super gacharange, and if a gacharange creature would be put into a zone other than the battle zone, return them to the bottom of your super gacharange.)"/>
      <property name="Watermark" value=""/>
      <property name="Mana" value="N/A"/>
      <property name="Rarity" value="Common"/>
      <property name="Number" value="15"/>
      <property name="Set" value="DMSD-13 Super GR Mega Start Deck: Joe's Super Jokers Tornado"/>
    </card>
    <card id="09647792-90ae-43b8-81fc-8bada143373a" name="Drill Doll">
      <property name="Format" value="OCG"/>
      <property name="Civilization" value="Water"/>
      <property name="Cost" value="3"/>
      <property name="Type" value="Gacharange Creature"/>
      <property name="Race" value="Jokers/Wonderforce"/>
      <property name="Power" value="2000+"/>
      <property name="Rules" value="■ Whenever this creature attacks, you may jokers tornado. If you do, this creature gets +3000 power and can't be blocked until the end of the turn. {JOKERS TORNADO} Return one of your other Jokers to your hand&#xA;(At the start of the game, gacharange creatures aren't put into your deck and are put into your super gacharange, and if a gacharange creature would be put into a zone other than the battle zone, return them to the bottom of your super gacharange.)"/>
      <property name="Watermark" value=""/>
      <property name="Mana" value="N/A"/>
      <property name="Rarity" value="Common"/>
      <property name="Number" value="16"/>
      <property name="Set" value="DMSD-13 Super GR Mega Start Deck: Joe's Super Jokers Tornado"/>
    </card>
    <card id="46302730-216a-4696-8095-f940d902bf96" name="Kurupicadiskun">
      <property name="Format" value="OCG"/>
      <property name="Civilization" value="Water"/>
      <property name="Cost" value="2"/>
      <property name="Type" value="Gacharange Creature"/>
      <property name="Race" value="Jokers/Wonderforce"/>
      <property name="Power" value="1000"/>
      <property name="Rules" value="■ Whenever this creature attacks, you may jokers tornado. If you do, choose one of your opponent's creatures. Until the start of your next turn, that creature can't attack or block. {JOKERS TORNADO} Return one of your other Jokers to your hand&#xA;(At the start of the game, gacharange creatures aren't put into your deck and are put into your super gacharange, and if a gacharange creature would be put into a zone other than the battle zone, return them to the bottom of your super gacharange.)"/>
      <property name="Watermark" value=""/>
      <property name="Mana" value="N/A"/>
      <property name="Rarity" value="Common"/>
      <property name="Number" value="17"/>
      <property name="Set" value="DMSD-13 Super GR Mega Start Deck: Joe's Super Jokers Tornado"/>
    </card>
    <card id="282c933f-1302-44bb-b682-2bb1ca467c07" name="Kanbee, Okehazama">
      <property name="Format" value="OCG"/>
      <property name="Civilization" value="Water"/>
      <property name="Cost" value="3"/>
      <property name="Type" value="Creature"/>
      <property name="Race" value="Jokers/Wonderforce"/>
      <property name="Power" value="3000"/>
      <property name="Rules" value="{BLOCKER} (You may tap this creature to change the attack target of your opponent's creature to this creature.)&#xA;■ This creature can't attack.&#xA;■ When you put this creature into the battle zone, gacharange summon. ({GACHARANGE SUMMON}: Summon the top card of your super gacharange with its cost paid.)"/>
      <property name="Watermark" value=""/>
      <property name="Mana" value="1"/>
      <property name="Rarity" value="Common"/>
      <property name="Number" value="18"/>
      <property name="Set" value="DMSD-13 Super GR Mega Start Deck: Joe's Super Jokers Tornado"/>
    </card>
    <card id="f00220ff-1483-48d9-ae3d-6e3ac10ff1d7" name="Dekin Duck">
      <property name="Format" value="OCG"/>
      <property name="Civilization" value="Water"/>
      <property name="Cost" value="2"/>
      <property name="Type" value="Creature"/>
      <property name="Race" value="Jokers"/>
      <property name="Power" value="1000"/>
      <property name="Rules" value="■ Whenever this creature attacks, you may jokers tornado. If you do, choose one of your opponent's creatures that have power 6000 or less and return it to its owner's hand. {JOKERS TORNADO} Return one of your other Jokers to your hand"/>
      <property name="Watermark" value=""/>
      <property name="Mana" value="1"/>
      <property name="Rarity" value="Common"/>
      <property name="Number" value="19"/>
      <property name="Set" value="DMSD-13 Super GR Mega Start Deck: Joe's Super Jokers Tornado"/>
    </card>
    <card id="4289297d-4034-4e62-8e10-bcf485ea9e09" name="Tom's Jelly">
      <property name="Format" value="OCG"/>
      <property name="Civilization" value="Water"/>
      <property name="Cost" value="1"/>
      <property name="Type" value="Creature"/>
      <property name="Race" value="Jokers"/>
      <property name="Power" value="1000"/>
      <property name="Rules" value="{BLOCKER} (You may tap this creature to change the attack target of your opponent's creature to this creature.)&#xA;■ This creature can't attack.&#xA;■ When this creature leaves the battle zone, draw a card."/>
      <property name="Watermark" value=""/>
      <property name="Mana" value="1"/>
      <property name="Rarity" value="Common"/>
      <property name="Number" value="20"/>
      <property name="Set" value="DMSD-13 Super GR Mega Start Deck: Joe's Super Jokers Tornado"/>
    </card>
  </cards>
</set>